chatsnip/__init__.py
chatsnip/chatsnip.py
chatsnip/extract_chat.py
chatsnip/extractor.py
chatsnip/file_splitter.py
chatsnip/flask_app.py
chatsnip/streamlit_ui.py
chatsnip-1.1.0.dist-info/METADATA
chatsnip-1.1.0.dist-info/WHEEL
chatsnip-1.1.0.dist-info/entry_points.txt
chatsnip-1.1.0.dist-info/top_level.txt
chatsnip-1.1.0.dist-info/RECORD
