Metadata-Version: 2.1
Name: chatsnip
Version: 1.1.0
Summary: A tool for extracting and managing chat data from HTML files. It includes a file splitter function to split up large files so they can be loaded back into ChatGPT if needed.
Home-page: https://github.com/leighvdveen/chatsnip
Author: Leigh-Anne Wells
Author-email: leighanne.vdveen@gmail.com
Classifier: Programming Language :: Python :: 3
Classifier: License :: OSI Approved :: MIT License
Classifier: Operating System :: OS Independent
Requires-Python: >=3.6
Requires-Dist: Flask
Requires-Dist: streamlit
Requires-Dist: ijson
Requires-Dist: Werkzeug
